jsonstore/__init__.py
jsonstore/fields.py
jsonstore/queryset.py
django_jsonstore-0.5.1.dist-info/LICENSE
django_jsonstore-0.5.1.dist-info/LICENSE_EXCEPTION
django_jsonstore-0.5.1.dist-info/METADATA
django_jsonstore-0.5.1.dist-info/WHEEL
django_jsonstore-0.5.1.dist-info/top_level.txt
django_jsonstore-0.5.1.dist-info/RECORD
